erose/__init__.py
erose/astromorth.py
erose/blob_extractor.py
erose/convolver_runner.py
erose/distance_selector.py
erose/isochrone_cutter.py
erose/kernels.py
erose/map_processing.py
erose-0.0.0.dist-info/licenses/LICENSE
erose-0.0.0.dist-info/METADATA
erose-0.0.0.dist-info/WHEEL
erose-0.0.0.dist-info/top_level.txt
erose-0.0.0.dist-info/RECORD
