Metadata-Version: 2.4
Name: erose
Version: 0.0.0
Summary: Enhancing Rapidly Overdensities of Sources with Ease
Author-email: Samuel Rusterucci <samuel.rusterucci@astro.unistra.fr>
License-Expression: MIT
Requires-Python: >=3.9
License-File: LICENSE
Dynamic: license-file
